nb2l/__init__.py
nb2l/core.py
nb2l/nb2l.py
nb2l/test_nb2l.py
nb2l-1.2.dist-info/METADATA
nb2l-1.2.dist-info/WHEEL
nb2l-1.2.dist-info/entry_points.txt
nb2l-1.2.dist-info/top_level.txt
nb2l-1.2.dist-info/RECORD
