Metadata-Version: 2.1
Name: nb2l
Version: 1.2
Summary: Convert numbers to literal French text.
Home-page: https://github.com/flashcode/nb2l
Author: Sébastien Helleu
Author-email: flashcode@flashtux.org
License: GPL3
Keywords: number literal french
Platform: UNKNOWN
Classifier: Development Status :: 5 - Production/Stable
Classifier: Environment :: Console
Classifier: Intended Audience :: Developers
Classifier: License :: OSI Approved :: GNU General Public License v3 or later (GPLv3+)
Classifier: Natural Language :: French
Classifier: Operating System :: OS Independent
Classifier: Programming Language :: Python
Classifier: Programming Language :: Python :: 3
Classifier: Topic :: Scientific/Engineering :: Mathematics
